abtoast/__init__.py
abtoast/utils.py
abtoast-0.0.1.dist-info/LICENSE
abtoast-0.0.1.dist-info/METADATA
abtoast-0.0.1.dist-info/WHEEL
abtoast-0.0.1.dist-info/top_level.txt
abtoast-0.0.1.dist-info/RECORD
